setup.cfg
setup.py
zicbee_mpris/__init__.py
zicbee_mpris/core.py
zicbee_mpris/mprisremote.py
zicbee_mpris.egg-info/PKG-INFO
zicbee_mpris.egg-info/SOURCES.txt
zicbee_mpris.egg-info/dependency_links.txt
zicbee_mpris.egg-info/entry_points.txt
zicbee_mpris.egg-info/top_level.txt